pyoui_db.py
pyoui_db-1.1.dist-info/LICENSE
pyoui_db-1.1.dist-info/METADATA
pyoui_db-1.1.dist-info/WHEEL
pyoui_db-1.1.dist-info/top_level.txt
pyoui_db-1.1.dist-info/RECORD
