Metadata-Version: 2.1
Name: pyoui_db
Version: 1.1
Summary: Python package providing a dictionary containing MAC address Organizationally Unique Identifiers (OUIs)
Author-email: Tomas Illuminati <tomiluminati@gmail.com>
Project-URL: Homepage, https://github.com/tomasilluminati/pyoui-db
Project-URL: Issues, https://github.com/pypa/sampleproject/issues
Classifier: Programming Language :: Python :: 3
Classifier: License :: OSI Approved :: MIT License
Classifier: Operating System :: OS Independent
Requires-Python: >=3.11
License-File: LICENSE
